{
  "date": "2026年7月8日 周三",
  "dayCount": "Day 189",
  "slogan": "每天10分钟｜提升认知｜连接世界｜改变自己",
  "ops": {
    "model": "LTV计算",
    "icon": "📊",
    "desc": "LTV计算用于预测用户生命周期内产生的总价值，帮助制定精准运营策略。联通可通过分析用户消费行为，识别高价值用户并优化资源投入。",
    "flow": [
      "1. 收集用户历史消费数据（月均ARPU、在网时长等）",
      "2. 计算平均用户生命周期（如流失率倒推）",
      "3. LTV = 平均ARPU × 平均生命周期（月）"
    ],
    "insight": "联通可针对LTV>1000元的用户推出专属储量权益（如额外流量包、积分加速），提升留存与续费率。"
  },
  "psych": {
    "concept": "互惠原则",
    "icon": "🤝",
    "def": "互惠原则指人们受到他人恩惠后会产生回报的心理倾向。",
    "quote": "例如：联通向用户赠送3天免费加速包，用户随后更可能购买正式套餐。",
    "insight": "在用户犹豫续费时，先提供免费体验（如5G速率升级），利用互惠心理促使下单。"
  },
  "biz": {
    "topic": "用户终身价值LTV",
    "icon": "💎",
    "desc": "LTV是用户从开始到停止使用产品期间贡献的总利润。联通需关注高LTV用户以最大化长期收益。",
    "stat1label": "月均ARPU",
    "stat1pct": 75,
    "stat1val": "75元",
    "stat2label": "平均在网时长",
    "stat2pct": 35,
    "stat2val": "35个月",
    "insight": "提升用户生命周期（如通过合约计划）可显著增加LTV，建议设计2年合约送终端优惠。"
  },
  "global": {
    "title": "美联储7月会议纪要显示分歧，市场押注9月降息概率升至65%",
    "icon": "🌍",
    "what": "美联储7月会议纪要显示，部分官员认为通胀回落速度放缓，但多数支持维持利率不变。市场解读为鸽派信号，降息预期升温。",
    "why": "美国通胀数据连续两个月高于预期，但就业市场出现降温迹象，美联储内部对下一步行动存在分歧。",
    "impact": "若9月降息，全球资金可能流向新兴市场，推动人民币升值，降低进口成本但影响出口竞争力。",
    "newsTime": "2026-07-07 14:00",
    "newsSource": "Reuters"
  },
  "tech": {
    "company": "苹果",
    "logo": "A",
    "logoBg": "#555555",
    "news": "iOS 27 Beta 3 发布：Siri更智能，新增多项功能",
    "desc": "苹果继续完善iOS 27，第三个测试版包含新功能，如Siri升级等，预计9月正式推送。",
    "insight": "联通可针对iOS 27的新Siri能力，设计语音办理业务场景（如查询流量、充值），提升用户体验。",
    "newsTime": "7月7日 06:19",
    "newsSource": "MacRumors"
  },
  "ent": {
    "title": "《黑神话：悟空》DLC「再战天庭」销量破500万，国产游戏里程碑",
    "icon": "🎮",
    "desc": "该DLC于6月30日发售，凭借极致画面和剧情引发全球玩家热议，成为暑期档最热游戏。",
    "quote": "游戏科学用实力证明，中国故事也能征服全球玩家。",
    "stars": "★★★★★"
  },
  "english": {
    "words": [
      {
        "word": "retention",
        "phonetic": "/rɪˈtenʃn/",
        "pron": "瑞-腾-申",
        "mean": "留存率"
      },
      {
        "word": "churn",
        "phonetic": "/tʃɜːrn/",
        "pron": "彻恩",
        "mean": "流失"
      },
      {
        "word": "upsell",
        "phonetic": "/ˈʌpsel/",
        "pron": "阿普-赛欧",
        "mean": "追加销售"
      }
    ],
    "example": "To improve **retention**, we need to reduce **churn** and identify opportunities for **upsell**. ",
    "exampleCN": "为提高留存率，我们需要减少流失并识别追加销售的机会。"
  },
  "japanese": {
    "words": [
      {
        "ja": "継続",
        "kana": "けいぞく",
        "romaji": "keizoku",
        "pron": "凯-佐-库",
        "mean": "持续、续约"
      },
      {
        "ja": "解約",
        "kana": "かいやく",
        "romaji": "kaiyaku",
        "pron": "卡伊-亚库",
        "mean": "解约、取消"
      },
      {
        "ja": "アップセル",
        "kana": "アップセル",
        "romaji": "appuseru",
        "pron": "阿普-瑟鲁",
        "mean": "追加销售"
      }
    ],
    "example": "**継続**率を上げるためには、**解約**を減らし、**アップセル**の機会を増やす必要があります。",
    "exampleCN": "为提高续约率，需要减少解约并增加追加销售的机会。"
  },
  "ai": {
    "topic": "具身智能",
    "node1": "🤖",
    "node2": "🧠",
    "node3": "⚡",
    "desc": "具身智能指AI在物理世界中有身体并感知交互的能力，如人形机器人。",
    "insight": "联通可布局5G+具身智能，为机器人提供低时延控制服务，如远程巡检、仓储物流场景。"
  },
  "think": {
    "question": "如果你来设计一个提升用户LTV的运营活动，最可能采用哪种方式？",
    "tags": [
      "A. 推出长期合约赠送终端",
      "B. 增加积分兑换权益",
      "C. 提供个性化套餐推荐",
      "D. 开展用户社群运营"
    ]
  },
  "worldcup": {
    "phase": "小组赛",
    "daysToFinal": 10,
    "todayDate": "7月8日",
    "tomorrowDate": "7月9日",
    "finished": [
      {
        "time": "00:00",
        "group": "",
        "venue": "",
        "home": "阿根廷",
        "homeflag": "🇦🇷",
        "away": "埃及",
        "awayflag": "🇪🇬",
        "score": "3-2"
      },
      {
        "time": "04:00",
        "group": "",
        "venue": "",
        "home": "瑞士",
        "homeflag": "🇨🇭",
        "away": "哥伦比亚",
        "awayflag": "🇨🇴",
        "score": "4-3"
      }
    ],
    "todayScheduled": [],
    "tomorrow": []
  },
  "generatedAt": "2026-07-08 07:05"
}