{
  "date": "2026年6月20日 周六",
  "dayCount": "Day 171",
  "slogan": "每天10分钟｜提升认知｜连接世界｜改变自己",
  "ops": {
    "model": "AARRR漏斗",
    "icon": "📊",
    "desc": "AARRR模型覆盖用户全生命周期，从获客到变现，适合精细化运营。",
    "flow": [
      "获取用户",
      "激活用户",
      "提升留存",
      "增加收入",
      "促进传播"
    ],
    "insight": "联通储量专区可针对高价值用户设计专属权益包，通过AARRR漏斗分析各环节转化率，重点优化激活与留存。"
  },
  "psych": {
    "concept": "峰终定律",
    "icon": "🧠",
    "def": "人们对体验的记忆由高峰时刻和结束时刻决定。",
    "quote": "例如在用户投诉处理中，快速解决问题（峰）和友好结束（终）能提升整体满意度。",
    "insight": "在用户充值或办理业务后，设计一个惊喜奖励（如流量赠送）作为高峰，并以感谢信息收尾，提升转化率。"
  },
  "biz": {
    "topic": "复利效应",
    "icon": "💰",
    "desc": "复利效应指初始投资产生的利息再投资，实现指数增长。用于用户运营，持续的小动作带来长期大回报。",
    "stat1label": "日活跃用户增长率",
    "stat1pct": 75,
    "stat1val": "2.3%",
    "stat2label": "月均用户留存率",
    "stat2pct": 35,
    "stat2val": "68%",
    "insight": "每天优化一个用户触点，如推送个性化优惠，长期积累将显著提升活跃度和收入。"
  },
  "global": {
    "title": "全球多国央行讨论数字货币跨境支付标准",
    "icon": "🌍",
    "what": "国际清算银行组织多国央行会议，推进央行数字货币（CBDC）的跨境支付互操作性标准。",
    "why": "数字货币可降低跨境支付成本，提升效率，各国希望争夺标准制定权。",
    "impact": "普通用户未来跨境转账可能更快捷、费用更低，但隐私和监管问题需关注。",
    "newsTime": "2026-06-19",
    "newsSource": "Reuters"
  },
  "tech": {
    "company": "索尼",
    "logo": "S",
    "logoBg": "#0033a0",
    "news": "索尼将“PC”从PlayStation业务战略中移除，新增“AI”",
    "desc": "索尼在官方业务战略摘要中删除了“PC”关键词，加入“AI”，同时PlayStation部门员工人数自2023年以来首次增长。",
    "insight": "索尼转向AI可能意味着PlayStation将更深度集成AI技术，如智能游戏推荐、个性化运营，联通可借鉴其数据驱动模式。",
    "newsTime": "6月19日 07:43",
    "newsSource": "Gamefile.news"
  },
  "ent": {
    "title": "2026年戛纳电影节获奖影片《星际迷途》引发热议",
    "icon": "🎬",
    "desc": "科幻片《星际迷途》斩获金棕榈奖，探讨人类在宇宙中的孤独与连接。",
    "quote": "连接宇宙，也连接内心。",
    "stars": "★★★★☆"
  },
  "english": {
    "words": [
      {
        "word": "resilience",
        "phonetic": "/rɪˈzɪliəns/",
        "pron": "瑞-兹-里-恩-斯",
        "mean": "韧性"
      },
      {
        "word": "algorithm",
        "phonetic": "/ˈælɡərɪðəm/",
        "pron": "阿尔-哥-瑞-森",
        "mean": "算法"
      },
      {
        "word": "monopoly",
        "phonetic": "/məˈnɒpəli/",
        "pron": "莫-诺-波-里",
        "mean": "垄断"
      }
    ],
    "example": "The company's **resilience** came from its unique **algorithm** that broke the market **monopoly**.",
    "exampleCN": "该公司的韧性源于其独特的算法，打破了市场垄断。"
  },
  "japanese": {
    "words": [
      {
        "ja": "絆",
        "kana": "きずな",
        "romaji": "kizuna",
        "pron": "ki-zu-na",
        "mean": "纽带"
      },
      {
        "ja": "進化",
        "kana": "しんか",
        "romaji": "shinka",
        "pron": "shin-ka",
        "mean": "进化"
      },
      {
        "ja": "挑戦",
        "kana": "ちょうせん",
        "romaji": "chousen",
        "pron": "choo-sen",
        "mean": "挑战"
      }
    ],
    "example": "5G技術の**進化**が人々の**絆**を強め、新しい**挑戦**を可能にした。",
    "exampleCN": "5G技术的进化加强了人们的纽带，使新的挑战成为可能。"
  },
  "ai": {
    "topic": "AI Agent自主代理",
    "node1": "🤖",
    "node2": "🔄",
    "node3": "🎯",
    "desc": "AI Agent能自主感知环境、制定计划并执行任务，无需人工干预。",
    "insight": "联通可用AI Agent自动处理用户常见问题，如流量查询、套餐变更，降低客服成本，提升响应速度。"
  },
  "think": {
    "question": "如何利用AI Agent提升联通用户的留存率？",
    "tags": [
      "个性化推荐",
      "自动续费提醒",
      "智能客服",
      "权益推送"
    ]
  },
  "worldcup": {
    "phase": "小组赛",
    "daysToFinal": 28,
    "todayDate": "6月20日",
    "tomorrowDate": "6月21日",
    "finished": [
      {
        "time": "03:00",
        "group": "GROUP_D组",
        "venue": "",
        "home": "美国",
        "homeflag": "🇺🇸",
        "away": "澳大利亚",
        "awayflag": "🇦🇺",
        "score": "2-0"
      },
      {
        "time": "06:00",
        "group": "GROUP_C组",
        "venue": "",
        "home": "苏格兰",
        "homeflag": "🏴󠁧󠁢󠁳󠁣󠁴󠁿",
        "away": "摩洛哥",
        "awayflag": "🇲🇦",
        "score": "0-1"
      }
    ],
    "todayScheduled": [
      {
        "time": "08:30",
        "group": "GROUP_C组",
        "venue": "",
        "home": "巴西",
        "homeflag": "🇧🇷",
        "away": "海地",
        "awayflag": "🇭🇹"
      },
      {
        "time": "11:00",
        "group": "GROUP_D组",
        "venue": "",
        "home": "土耳其",
        "homeflag": "🇹🇷",
        "away": "巴拉圭",
        "awayflag": "🇵🇾"
      }
    ],
    "tomorrow": [
      {
        "time": "01:00",
        "group": "GROUP_F组",
        "venue": "",
        "home": "荷兰",
        "homeflag": "🇳🇱",
        "away": "瑞典",
        "awayflag": "🇸🇪",
        "winPct": 55,
        "drawPct": 25,
        "losePct": 20
      },
      {
        "time": "04:00",
        "group": "GROUP_E组",
        "venue": "",
        "home": "德国",
        "homeflag": "🇩🇪",
        "away": "科特迪瓦",
        "awayflag": "🇨🇮",
        "winPct": 60,
        "drawPct": 20,
        "losePct": 20
      },
      {
        "time": "08:00",
        "group": "GROUP_E组",
        "venue": "",
        "home": "厄瓜多尔",
        "homeflag": "🇪🇨",
        "away": "库拉索",
        "awayflag": "🇨🇼",
        "winPct": 50,
        "drawPct": 30,
        "losePct": 20
      },
      {
        "time": "12:00",
        "group": "GROUP_F组",
        "venue": "",
        "home": "突尼斯",
        "homeflag": "🇹🇳",
        "away": "日本",
        "awayflag": "🇯🇵",
        "winPct": 45,
        "drawPct": 30,
        "losePct": 25
      }
    ]
  },
  "generatedAt": "2026-06-20 09:57"
}